Workbook

Sheet Payroll Dashboard
A1: AVERRA — PAYROLL DASHBOARD
A2: Enter a payroll year in B3. Totals are drawn from Monthly Payroll rows 3–202.
A3: Payroll Year | B3: 2026
D4: Monthly gross pay
A5: Gross Pay (GBP) | B5: =SUMIFS('Monthly Payroll'!$L$3:$L$202,'Monthly Payroll'!$B$3:$B$202,">="&DATE($B$3,1,1),'Monthly Payroll'!$B$3:$B$202,"<"&DATE($B$3+1,1,1)) | D5: Month | E5: Gross Pay (GBP)
A6: PAYE (GBP) | B6: =SUMIFS('Monthly Payroll'!$M$3:$M$202,'Monthly Payroll'!$B$3:$B$202,">="&DATE($B$3,1,1),'Monthly Payroll'!$B$3:$B$202,"<"&DATE($B$3+1,1,1)) | D6: =DATE($B$3,1,1) | E6: =SUMIFS('Monthly Payroll'!$L$3:$L$202,'Monthly Payroll'!$B$3:$B$202,">="&D6,'Monthly Payroll'!$B$3:$B$202,"<"&EDATE(D6,1))
A7: Employee NI (GBP) | B7: =SUMIFS('Monthly Payroll'!$N$3:$N$202,'Monthly Payroll'!$B$3:$B$202,">="&DATE($B$3,1,1),'Monthly Payroll'!$B$3:$B$202,"<"&DATE($B$3+1,1,1)) | D7: =DATE($B$3,2,1) | E7: =SUMIFS('Monthly Payroll'!$L$3:$L$202,'Monthly Payroll'!$B$3:$B$202,">="&D7,'Monthly Payroll'!$B$3:$B$202,"<"&EDATE(D7,1))
A8: Employee Pension (GBP) | B8: =SUMIFS('Monthly Payroll'!$O$3:$O$202,'Monthly Payroll'!$B$3:$B$202,">="&DATE($B$3,1,1),'Monthly Payroll'!$B$3:$B$202,"<"&DATE($B$3+1,1,1)) | D8: =DATE($B$3,3,1) | E8: =SUMIFS('Monthly Payroll'!$L$3:$L$202,'Monthly Payroll'!$B$3:$B$202,">="&D8,'Monthly Payroll'!$B$3:$B$202,"<"&EDATE(D8,1))
A9: Net Pay (GBP) | B9: =SUMIFS('Monthly Payroll'!$R$3:$R$202,'Monthly Payroll'!$B$3:$B$202,">="&DATE($B$3,1,1),'Monthly Payroll'!$B$3:$B$202,"<"&DATE($B$3+1,1,1)) | D9: =DATE($B$3,4,1) | E9: =SUMIFS('Monthly Payroll'!$L$3:$L$202,'Monthly Payroll'!$B$3:$B$202,">="&D9,'Monthly Payroll'!$B$3:$B$202,"<"&EDATE(D9,1))
A10: Employer NI (GBP) | B10: =SUMIFS('Monthly Payroll'!$S$3:$S$202,'Monthly Payroll'!$B$3:$B$202,">="&DATE($B$3,1,1),'Monthly Payroll'!$B$3:$B$202,"<"&DATE($B$3+1,1,1)) | D10: =DATE($B$3,5,1) | E10: =SUMIFS('Monthly Payroll'!$L$3:$L$202,'Monthly Payroll'!$B$3:$B$202,">="&D10,'Monthly Payroll'!$B$3:$B$202,"<"&EDATE(D10,1))
A11: Employer Pension (GBP) | B11: =SUMIFS('Monthly Payroll'!$T$3:$T$202,'Monthly Payroll'!$B$3:$B$202,">="&DATE($B$3,1,1),'Monthly Payroll'!$B$3:$B$202,"<"&DATE($B$3+1,1,1)) | D11: =DATE($B$3,6,1) | E11: =SUMIFS('Monthly Payroll'!$L$3:$L$202,'Monthly Payroll'!$B$3:$B$202,">="&D11,'Monthly Payroll'!$B$3:$B$202,"<"&EDATE(D11,1))
A12: Total Employer Cost (GBP) | B12: =SUMIFS('Monthly Payroll'!$U$3:$U$202,'Monthly Payroll'!$B$3:$B$202,">="&DATE($B$3,1,1),'Monthly Payroll'!$B$3:$B$202,"<"&DATE($B$3+1,1,1)) | D12: =DATE($B$3,7,1) | E12: =SUMIFS('Monthly Payroll'!$L$3:$L$202,'Monthly Payroll'!$B$3:$B$202,">="&D12,'Monthly Payroll'!$B$3:$B$202,"<"&EDATE(D12,1))
A13: Pending / Unpaid Payroll Rows | B13: =COUNTIF('Monthly Payroll'!$W$3:$W$202,"Pending") | D13: =DATE($B$3,8,1) | E13: =SUMIFS('Monthly Payroll'!$L$3:$L$202,'Monthly Payroll'!$B$3:$B$202,">="&D13,'Monthly Payroll'!$B$3:$B$202,"<"&EDATE(D13,1))
A14: Active Employee Records | B14: =COUNTIF('Employee Database'!$Q$3:$Q$202,"Active") | D14: =DATE($B$3,9,1) | E14: =SUMIFS('Monthly Payroll'!$L$3:$L$202,'Monthly Payroll'!$B$3:$B$202,">="&D14,'Monthly Payroll'!$B$3:$B$202,"<"&EDATE(D14,1))
D15: =DATE($B$3,10,1) | E15: =SUMIFS('Monthly Payroll'!$L$3:$L$202,'Monthly Payroll'!$B$3:$B$202,">="&D15,'Monthly Payroll'!$B$3:$B$202,"<"&EDATE(D15,1))
D16: =DATE($B$3,11,1) | E16: =SUMIFS('Monthly Payroll'!$L$3:$L$202,'Monthly Payroll'!$B$3:$B$202,">="&D16,'Monthly Payroll'!$B$3:$B$202,"<"&EDATE(D16,1))
D17: =DATE($B$3,12,1) | E17: =SUMIFS('Monthly Payroll'!$L$3:$L$202,'Monthly Payroll'!$B$3:$B$202,">="&D17,'Monthly Payroll'!$B$3:$B$202,"<"&EDATE(D17,1))

Sheet Employee Database
A1: AVERRA STAFFING SOLUTIONS LTD
A2: Employee ID | B2: Full Name | C2: Job Title | D2: Department | E2: Work Country | F2: Worker Type | G2: Start Date | H2: End Date | I2: Pay Frequency | J2: Annual Salary (GBP) | K2: Hourly Rate (GBP) | L2: Employee Pension % | M2: Employer Pension % | N2: Tax Code | O2: NI Category | P2: Email | Q2: Status | R2: Notes
Q3: =IF(B3="","",IF(H3<>"","Inactive","Active"))
Q4: =IF(B4="","",IF(H4<>"","Inactive","Active"))
Q5: =IF(B5="","",IF(H5<>"","Inactive","Active"))
Q6: =IF(B6="","",IF(H6<>"","Inactive","Active"))
Q7: =IF(B7="","",IF(H7<>"","Inactive","Active"))
Q8: =IF(B8="","",IF(H8<>"","Inactive","Active"))
Q9: =IF(B9="","",IF(H9<>"","Inactive","Active"))
Q10: =IF(B10="","",IF(H10<>"","Inactive","Active"))
Q11: =IF(B11="","",IF(H11<>"","Inactive","Active"))
Q12: =IF(B12="","",IF(H12<>"","Inactive","Active"))
Q13: =IF(B13="","",IF(H13<>"","Inactive","Active"))
Q14: =IF(B14="","",IF(H14<>"","Inactive","Active"))
... Q202: =IF(B202="","",IF(H202<>"","Inactive","Active"))
A204: Use a unique Employee ID. Store only necessary personal data; protect this workbook and restrict access.

Sheet Monthly Payroll
A1: AVERRA — MONTHLY PAYROLL REGISTER
A2: Payroll ID | B2: Period Start | C2: Period End | D2: Pay Date | E2: Employee ID | F2: Employee Name | G2: Worker Type | H2: Pay Frequency | I2: Basic Pay (GBP) | J2: Overtime / Bonus (GBP) | K2: Other Earnings (GBP) | L2: Gross Pay (GBP) | M2: PAYE (GBP) | N2: Employee NI (GBP) | O2: Employee Pension (GBP) | P2: Other Deductions (GBP) | Q2: Total Deductions (GBP) | R2: Net Pay (GBP) | S2: Employer NI (GBP) | T2: Employer Pension (GBP) | U2: Total Employer Cost (GBP) | V2: Review Status | W2: Payment Status | X2: Notes
F3: =IFERROR(INDEX('Employee Database'!$B$3:$B$202,MATCH(E3,'Employee Database'!$A$3:$A$202,0)),"") | G3: =IFERROR(INDEX('Employee Database'!$F$3:$F$202,MATCH(E3,'Employee Database'!$A$3:$A$202,0)),"") | H3: =IFERROR(INDEX('Employee Database'!$I$3:$I$202,MATCH(E3,'Employee Database'!$A$3:$A$202,0)),"") | I3: =IFERROR(IF(H3="Monthly",INDEX('Employee Database'!$J$3:$J$202,MATCH(E3,'Employee Database'!$A$3:$A$202,0))/12,IF(H3="Weekly",INDEX('Employee Database'!$J$3:$J$202,MATCH(E3,'Employee Database'!$A$3:$A$202,0))/52,IF(H3="Fortnightly",INDEX('Employee Database'!$J$3:$J$202,MATCH(E3,'Employee Database'!$A$3:$A$202,0))/26,IF(H3="Four-weekly",INDEX('Employee Database'!$J$3:$J$202,MATCH(E3,'Employee Database'!$A$3:$A$202,0))/13,0))))),0) | L3: =SUM(I3:K3) | O3: =IFERROR(ROUND(L3*INDEX('Employee Database'!$L$3:$L$202,MATCH(E3,'Employee Database'!$A$3:$A$202,0))/100,2),0) | Q3: =SUM(M3:P3) | R3: =L3-Q3 | T3: =IFERROR(ROUND(L3*INDEX('Employee Database'!$M$3:$M$202,MATCH(E3,'Employee Database'!$A$3:$A$202,0))/100,2),0) | U3: =SUM(L3,S3,T3) | V3: =IF(E3="","",IF(OR(B3="",C3="",D3=""),"Missing period/date",IF(L3<0,"Check gross pay",IF(R3<0,"Deductions exceed gross","Review statutory amounts"))))
F4: =IFERROR(INDEX('Employee Database'!$B$3:$B$202,MATCH(E4,'Employee Database'!$A$3:$A$202,0)),"") | G4: =IFERROR(INDEX('Employee Database'!$F$3:$F$202,MATCH(E4,'Employee Database'!$A$3:$A$202,0)),"") | H4: =IFERROR(INDEX('Employee Database'!$I$3:$I$202,MATCH(E4,'Employee Database'!$A$3:$A$202,0)),"") | I4: =IFERROR(IF(H4="Monthly",INDEX('Employee Database'!$J$3:$J$202,MATCH(E4,'Employee Database'!$A$3:$A$202,0))/12,IF(H4="Weekly",INDEX('Employee Database'!$J$3:$J$202,MATCH(E4,'Employee Database'!$A$3:$A$202,0))/52,IF(H4="Fortnightly",INDEX('Employee Database'!$J$3:$J$202,MATCH(E4,'Employee Database'!$A$3:$A$202,0))/26,IF(H4="Four-weekly",INDEX('Employee Database'!$J$3:$J$202,MATCH(E4,'Employee Database'!$A$3:$A$202,0))/13,0))))),0) | L4: =SUM(I4:K4) | O4: =IFERROR(ROUND(L4*INDEX('Employee Database'!$L$3:$L$202,MATCH(E4,'Employee Database'!$A$3:$A$202,0))/100,2),0) | Q4: =SUM(M4:P4) | R4: =L4-Q4 | T4: =IFERROR(ROUND(L4*INDEX('Employee Database'!$M$3:$M$202,MATCH(E4,'Employee Database'!$A$3:$A$202,0))/100,2),0) | U4: =SUM(L4,S4,T4) | V4: =IF(E4="","",IF(OR(B4="",C4="",D4=""),"Missing period/date",IF(L4<0,"Check gross pay",IF(R4<0,"Deductions exceed gross","Review statutory amounts"))))
F5: =IFERROR(INDEX('Employee Database'!$B$3:$B$202,MATCH(E5,'Employee Database'!$A$3:$A$202,0)),"") | G5: =IFERROR(INDEX('Employee Database'!$F$3:$F$202,MATCH(E5,'Employee Database'!$A$3:$A$202,0)),"") | H5: =IFERROR(INDEX('Employee Database'!$I$3:$I$202,MATCH(E5,'Employee Database'!$A$3:$A$202,0)),"") | I5: =IFERROR(IF(H5="Monthly",INDEX('Employee Database'!$J$3:$J$202,MATCH(E5,'Employee Database'!$A$3:$A$202,0))/12,IF(H5="Weekly",INDEX('Employee Database'!$J$3:$J$202,MATCH(E5,'Employee Database'!$A$3:$A$202,0))/52,IF(H5="Fortnightly",INDEX('Employee Database'!$J$3:$J$202,MATCH(E5,'Employee Database'!$A$3:$A$202,0))/26,IF(H5="Four-weekly",INDEX('Employee Database'!$J$3:$J$202,MATCH(E5,'Employee Database'!$A$3:$A$202,0))/13,0))))),0) | L5: =SUM(I5:K5) | O5: =IFERROR(ROUND(L5*INDEX('Employee Database'!$L$3:$L$202,MATCH(E5,'Employee Database'!$A$3:$A$202,0))/100,2),0) | Q5: =SUM(M5:P5) | R5: =L5-Q5 | T5: =IFERROR(ROUND(L5*INDEX('Employee Database'!$M$3:$M$202,MATCH(E5,'Employee Database'!$A$3:$A$202,0))/100,2),0) | U5: =SUM(L5,S5,T5) | V5: =IF(E5="","",IF(OR(B5="",C5="",D5=""),"Missing period/date",IF(L5<0,"Check gross pay",IF(R5<0,"Deductions exceed gross","Review statutory amounts"))))
F6: =IFERROR(INDEX('Employee Database'!$B$3:$B$202,MATCH(E6,'Employee Database'!$A$3:$A$202,0)),"") | G6: =IFERROR(INDEX('Employee Database'!$F$3:$F$202,MATCH(E6,'Employee Database'!$A$3:$A$202,0)),"") | H6: =IFERROR(INDEX('Employee Database'!$I$3:$I$202,MATCH(E6,'Employee Database'!$A$3:$A$202,0)),"") | I6: =IFERROR(IF(H6="Monthly",INDEX('Employee Database'!$J$3:$J$202,MATCH(E6,'Employee Database'!$A$3:$A$202,0))/12,IF(H6="Weekly",INDEX('Employee Database'!$J$3:$J$202,MATCH(E6,'Employee Database'!$A$3:$A$202,0))/52,IF(H6="Fortnightly",INDEX('Employee Database'!$J$3:$J$202,MATCH(E6,'Employee Database'!$A$3:$A$202,0))/26,IF(H6="Four-weekly",INDEX('Employee Database'!$J$3:$J$202,MATCH(E6,'Employee Database'!$A$3:$A$202,0))/13,0))))),0) | L6: =SUM(I6:K6) | O6: =IFERROR(ROUND(L6*INDEX('Employee Database'!$L$3:$L$202,MATCH(E6,'Employee Database'!$A$3:$A$202,0))/100,2),0) | Q6: =SUM(M6:P6) | R6: =L6-Q6 | T6: =IFERROR(ROUND(L6*INDEX('Employee Database'!$M$3:$M$202,MATCH(E6,'Employee Database'!$A$3:$A$202,0))/100,2),0) | U6: =SUM(L6,S6,T6) | V6: =IF(E6="","",IF(OR(B6="",C6="",D6=""),"Missing period/date",IF(L6<0,"Check gross pay",IF(R6<0,"Deductions exceed gross","Review statutory amounts"))))
F7: =IFERROR(INDEX('Employee Database'!$B$3:$B$202,MATCH(E7,'Employee Database'!$A$3:$A$202,0)),"") | G7: =IFERROR(INDEX('Employee Database'!$F$3:$F$202,MATCH(E7,'Employee Database'!$A$3:$A$202,0)),"") | H7: =IFERROR(INDEX('Employee Database'!$I$3:$I$202,MATCH(E7,'Employee Database'!$A$3:$A$202,0)),"") | I7: =IFERROR(IF(H7="Monthly",INDEX('Employee Database'!$J$3:$J$202,MATCH(E7,'Employee Database'!$A$3:$A$202,0))/12,IF(H7="Weekly",INDEX('Employee Database'!$J$3:$J$202,MATCH(E7,'Employee Database'!$A$3:$A$202,0))/52,IF(H7="Fortnightly",INDEX('Employee Database'!$J$3:$J$202,MATCH(E7,'Employee Database'!$A$3:$A$202,0))/26,IF(H7="Four-weekly",INDEX('Employee Database'!$J$3:$J$202,MATCH(E7,'Employee Database'!$A$3:$A$202,0))/13,0))))),0) | L7: =SUM(I7:K7) | O7: =IFERROR(ROUND(L7*INDEX('Employee Database'!$L$3:$L$202,MATCH(E7,'Employee Database'!$A$3:$A$202,0))/100,2),0) | Q7: =SUM(M7:P7) | R7: =L7-Q7 | T7: =IFERROR(ROUND(L7*INDEX('Employee Database'!$M$3:$M$202,MATCH(E7,'Employee Database'!$A$3:$A$202,0))/100,2),0) | U7: =SUM(L7,S7,T7) | V7: =IF(E7="","",IF(OR(B7="",C7="",D7=""),"Missing period/date",IF(L7<0,"Check gross pay",IF(R7<0,"Deductions exceed gross","Review statutory amounts"))))
F8: =IFERROR(INDEX('Employee Database'!$B$3:$B$202,MATCH(E8,'Employee Database'!$A$3:$A$202,0)),"") | G8: =IFERROR(INDEX('Employee Database'!$F$3:$F$202,MATCH(E8,'Employee Database'!$A$3:$A$202,0)),"") | H8: =IFERROR(INDEX('Employee Database'!$I$3:$I$202,MATCH(E8,'Employee Database'!$A$3:$A$202,0)),"") | I8: =IFERROR(IF(H8="Monthly",INDEX('Employee Database'!$J$3:$J$202,MATCH(E8,'Employee Database'!$A$3:$A$202,0))/12,IF(H8="Weekly",INDEX('Employee Database'!$J$3:$J$202,MATCH(E8,'Employee Database'!$A$3:$A$202,0))/52,IF(H8="Fortnightly",INDEX('Employee Database'!$J$3:$J$202,MATCH(E8,'Employee Database'!$A$3:$A$202,0))/26,IF(H8="Four-weekly",INDEX('Employee Database'!$J$3:$J$202,MATCH(E8,'Employee Database'!$A$3:$A$202,0))/13,0))))),0) | L8: =SUM(I8:K8) | O8: =IFERROR(ROUND(L8*INDEX('Employee Database'!$L$3:$L$202,MATCH(E8,'Employee Database'!$A$3:$A$202,0))/100,2),0) | Q8: =SUM(M8:P8) | R8: =L8-Q8 | T8: =IFERROR(ROUND(L8*INDEX('Employee Database'!$M$3:$M$202,MATCH(E8,'Employee Database'!$A$3:$A$202,0))/100,2),0) | U8: =SUM(L8,S8,T8) | V8: =IF(E8="","",IF(OR(B8="",C8="",D8=""),"Missing period/date",IF(L8<0,"Check gross pay",IF(R8<0,"Deductions exceed gross","Review statutory amounts"))))
F9: =IFERROR(INDEX('Employee Database'!$B$3:$B$202,MATCH(E9,'Employee Database'!$A$3:$A$202,0)),"") | G9: =IFERROR(INDEX('Employee Database'!$F$3:$F$202,MATCH(E9,'Employee Database'!$A$3:$A$202,0)),"") | H9: =IFERROR(INDEX('Employee Database'!$I$3:$I$202,MATCH(E9,'Employee Database'!$A$3:$A$202,0)),"") | I9: =IFERROR(IF(H9="Monthly",INDEX('Employee Database'!$J$3:$J$202,MATCH(E9,'Employee Database'!$A$3:$A$202,0))/12,IF(H9="Weekly",INDEX('Employee Database'!$J$3:$J$202,MATCH(E9,'Employee Database'!$A$3:$A$202,0))/52,IF(H9="Fortnightly",INDEX('Employee Database'!$J$3:$J$202,MATCH(E9,'Employee Database'!$A$3:$A$202,0))/26,IF(H9="Four-weekly",INDEX('Employee Database'!$J$3:$J$202,MATCH(E9,'Employee Database'!$A$3:$A$202,0))/13,0))))),0) | L9: =SUM(I9:K9) | O9: =IFERROR(ROUND(L9*INDEX('Employee Database'!$L$3:$L$202,MATCH(E9,'Employee Database'!$A$3:$A$202,0))/100,2),0) | Q9: =SUM(M9:P9) | R9: =L9-Q9 | T9: =IFERROR(ROUND(L9*INDEX('Employee Database'!$M$3:$M$202,MATCH(E9,'Employee Database'!$A$3:$A$202,0))/100,2),0) | U9: =SUM(L9,S9,T9) | V9: =IF(E9="","",IF(OR(B9="",C9="",D9=""),"Missing period/date",IF(L9<0,"Check gross pay",IF(R9<0,"Deductions exceed gross","Review statutory amounts"))))
F10: =IFERROR(INDEX('Employee Database'!$B$3:$B$202,MATCH(E10,'Employee Database'!$A$3:$A$202,0)),"") | G10: =IFERROR(INDEX('Employee Database'!$F$3:$F$202,MATCH(E10,'Employee Database'!$A$3:$A$202,0)),"") | H10: =IFERROR(INDEX('Employee Database'!$I$3:$I$202,MATCH(E10,'Employee Database'!$A$3:$A$202,0)),"") | I10: =IFERROR(IF(H10="Monthly",INDEX('Employee Database'!$J$3:$J$202,MATCH(E10,'Employee Database'!$A$3:$A$202,0))/12,IF(H10="Weekly",INDEX('Employee Database'!$J$3:$J$202,MATCH(E10,'Employee Database'!$A$3:$A$202,0))/52,IF(H10="Fortnightly",INDEX('Employee Database'!$J$3:$J$202,MATCH(E10,'Employee Database'!$A$3:$A$202,0))/26,IF(H10="Four-weekly",INDEX('Employee Database'!$J$3:$J$202,MATCH(E10,'Employee Database'!$A$3:$A$202,0))/13,0))))),0) | L10: =SUM(I10:K10) | O10: =IFERROR(ROUND(L10*INDEX('Employee Database'!$L$3:$L$202,MATCH(E10,'Employee Database'!$A$3:$A$202,0))/100,2),0) | Q10: =SUM(M10:P10) | R10: =L10-Q10 | T10: =IFERROR(ROUND(L10*INDEX('Employee Database'!$M$3:$M$202,MATCH(E10,'Employee Database'!$A$3:$A$202,0))/100,2),0) | U10: =SUM(L10,S10,T10) | V10: =IF(E10="","",IF(OR(B10="",C10="",D10=""),"Missing period/date",IF(L10<0,"Check gross pay",IF(R10<0,"Deductions exceed gross","Review statutory amounts"))))
F11: =IFERROR(INDEX('Employee Database'!$B$3:$B$202,MATCH(E11,'Employee Database'!$A$3:$A$202,0)),"") | G11: =IFERROR(INDEX('Employee Database'!$F$3:$F$202,MATCH(E11,'Employee Database'!$A$3:$A$202,0)),"") | H11: =IFERROR(INDEX('Employee Database'!$I$3:$I$202,MATCH(E11,'Employee Database'!$A$3:$A$202,0)),"") | I11: =IFERROR(IF(H11="Monthly",INDEX('Employee Database'!$J$3:$J$202,MATCH(E11,'Employee Database'!$A$3:$A$202,0))/12,IF(H11="Weekly",INDEX('Employee Database'!$J$3:$J$202,MATCH(E11,'Employee Database'!$A$3:$A$202,0))/52,IF(H11="Fortnightly",INDEX('Employee Database'!$J$3:$J$202,MATCH(E11,'Employee Database'!$A$3:$A$202,0))/26,IF(H11="Four-weekly",INDEX('Employee Database'!$J$3:$J$202,MATCH(E11,'Employee Database'!$A$3:$A$202,0))/13,0))))),0) | L11: =SUM(I11:K11) | O11: =IFERROR(ROUND(L11*INDEX('Employee Database'!$L$3:$L$202,MATCH(E11,'Employee Database'!$A$3:$A$202,0))/100,2),0) | Q11: =SUM(M11:P11) | R11: =L11-Q11 | T11: =IFERROR(ROUND(L11*INDEX('Employee Database'!$M$3:$M$202,MATCH(E11,'Employee Database'!$A$3:$A$202,0))/100,2),0) | U11: =SUM(L11,S11,T11) | V11: =IF(E11="","",IF(OR(B11="",C11="",D11=""),"Missing period/date",IF(L11<0,"Check gross pay",IF(R11<0,"Deductions exceed gross","Review statutory amounts"))))
F12: =IFERROR(INDEX('Employee Database'!$B$3:$B$202,MATCH(E12,'Employee Database'!$A$3:$A$202,0)),"") | G12: =IFERROR(INDEX('Employee Database'!$F$3:$F$202,MATCH(E12,'Employee Database'!$A$3:$A$202,0)),"") | H12: =IFERROR(INDEX('Employee Database'!$I$3:$I$202,MATCH(E12,'Employee Database'!$A$3:$A$202,0)),"") | I12: =IFERROR(IF(H12="Monthly",INDEX('Employee Database'!$J$3:$J$202,MATCH(E12,'Employee Database'!$A$3:$A$202,0))/12,IF(H12="Weekly",INDEX('Employee Database'!$J$3:$J$202,MATCH(E12,'Employee Database'!$A$3:$A$202,0))/52,IF(H12="Fortnightly",INDEX('Employee Database'!$J$3:$J$202,MATCH(E12,'Employee Database'!$A$3:$A$202,0))/26,IF(H12="Four-weekly",INDEX('Employee Database'!$J$3:$J$202,MATCH(E12,'Employee Database'!$A$3:$A$202,0))/13,0))))),0) | L12: =SUM(I12:K12) | O12: =IFERROR(ROUND(L12*INDEX('Employee Database'!$L$3:$L$202,MATCH(E12,'Employee Database'!$A$3:$A$202,0))/100,2),0) | Q12: =SUM(M12:P12) | R12: =L12-Q12 | T12: =IFERROR(ROUND(L12*INDEX('Employee Database'!$M$3:$M$202,MATCH(E12,'Employee Database'!$A$3:$A$202,0))/100,2),0) | U12: =SUM(L12,S12,T12) | V12: =IF(E12="","",IF(OR(B12="",C12="",D12=""),"Missing period/date",IF(L12<0,"Check gross pay",IF(R12<0,"Deductions exceed gross","Review statutory amounts"))))
F13: =IFERROR(INDEX('Employee Database'!$B$3:$B$202,MATCH(E13,'Employee Database'!$A$3:$A$202,0)),"") | G13: =IFERROR(INDEX('Employee Database'!$F$3:$F$202,MATCH(E13,'Employee Database'!$A$3:$A$202,0)),"") | H13: =IFERROR(INDEX('Employee Database'!$I$3:$I$202,MATCH(E13,'Employee Database'!$A$3:$A$202,0)),"") | I13: =IFERROR(IF(H13="Monthly",INDEX('Employee Database'!$J$3:$J$202,MATCH(E13,'Employee Database'!$A$3:$A$202,0))/12,IF(H13="Weekly",INDEX('Employee Database'!$J$3:$J$202,MATCH(E13,'Employee Database'!$A$3:$A$202,0))/52,IF(H13="Fortnightly",INDEX('Employee Database'!$J$3:$J$202,MATCH(E13,'Employee Database'!$A$3:$A$202,0))/26,IF(H13="Four-weekly",INDEX('Employee Database'!$J$3:$J$202,MATCH(E13,'Employee Database'!$A$3:$A$202,0))/13,0))))),0) | L13: =SUM(I13:K13) | O13: =IFERROR(ROUND(L13*INDEX('Employee Database'!$L$3:$L$202,MATCH(E13,'Employee Database'!$A$3:$A$202,0))/100,2),0) | Q13: =SUM(M13:P13) | R13: =L13-Q13 | T13: =IFERROR(ROUND(L13*INDEX('Employee Database'!$M$3:$M$202,MATCH(E13,'Employee Database'!$A$3:$A$202,0))/100,2),0) | U13: =SUM(L13,S13,T13) | V13: =IF(E13="","",IF(OR(B13="",C13="",D13=""),"Missing period/date",IF(L13<0,"Check gross pay",IF(R13<0,"Deductions exceed gross","Review statutory amounts"))))
F14: =IFERROR(INDEX('Employee Database'!$B$3:$B$202,MATCH(E14,'Employee Database'!$A$3:$A$202,0)),"") | G14: =IFERROR(INDEX('Employee Database'!$F$3:$F$202,MATCH(E14,'Employee Database'!$A$3:$A$202,0)),"") | H14: =IFERROR(INDEX('Employee Database'!$I$3:$I$202,MATCH(E14,'Employee Database'!$A$3:$A$202,0)),"") | I14: =IFERROR(IF(H14="Monthly",INDEX('Employee Database'!$J$3:$J$202,MATCH(E14,'Employee Database'!$A$3:$A$202,0))/12,IF(H14="Weekly",INDEX('Employee Database'!$J$3:$J$202,MATCH(E14,'Employee Database'!$A$3:$A$202,0))/52,IF(H14="Fortnightly",INDEX('Employee Database'!$J$3:$J$202,MATCH(E14,'Employee Database'!$A$3:$A$202,0))/26,IF(H14="Four-weekly",INDEX('Employee Database'!$J$3:$J$202,MATCH(E14,'Employee Database'!$A$3:$A$202,0))/13,0))))),0) | L14: =SUM(I14:K14) | O14: =IFERROR(ROUND(L14*INDEX('Employee Database'!$L$3:$L$202,MATCH(E14,'Employee Database'!$A$3:$A$202,0))/100,2),0) | Q14: =SUM(M14:P14) | R14: =L14-Q14 | T14: =IFERROR(ROUND(L14*INDEX('Employee Database'!$M$3:$M$202,MATCH(E14,'Employee Database'!$A$3:$A$202,0))/100,2),0) | U14: =SUM(L14,S14,T14) | V14: =IF(E14="","",IF(OR(B14="",C14="",D14=""),"Missing period/date",IF(L14<0,"Check gross pay",IF(R14<0,"Deductions exceed gross","Review statutory amounts"))))
... F202: =IFERROR(INDEX('Employee Database'!$B$3:$B$202,MATCH(E202,'Employee Database'!$A$3:$A$202,0)),"") | G202: =IFERROR(INDEX('Employee Database'!$F$3:$F$202,MATCH(E202,'Employee Database'!$A$3:$A$202,0)),"") | H202: =IFERROR(INDEX('Employee Database'!$I$3:$I$202,MATCH(E202,'Employee Database'!$A$3:$A$202,0)),"") | I202: =IFERROR(IF(H202="Monthly",INDEX('Employee Database'!$J$3:$J$202,MATCH(E202,'Employee Database'!$A$3:$A$202,0))/12,IF(H202="Weekly",INDEX('Employee Database'!$J$3:$J$202,MATCH(E202,'Employee Database'!$A$3:$A$202,0))/52,IF(H202="Fortnightly",INDEX('Employee Database'!$J$3:$J$202,MATCH(E202,'Employee Database'!$A$3:$A$202,0))/26,IF(H202="Four-weekly",INDEX('Employee Database'!$J$3:$J$202,MATCH(E202,'Employee Database'!$A$3:$A$202,0))/13,0))))),0) | L202: =SUM(I202:K202) | O202: =IFERROR(ROUND(L202*INDEX('Employee Database'!$L$3:$L$202,MATCH(E202,'Employee Database'!$A$3:$A$202,0))/100,2),0) | Q202: =SUM(M202:P202) | R202: =L202-Q202 | T202: =IFERROR(ROUND(L202*INDEX('Employee Database'!$M$3:$M$202,MATCH(E202,'Employee Database'!$A$3:$A$202,0))/100,2),0) | U202: =SUM(L202,S202,T202) | V202: =IF(E202="","",IF(OR(B202="",C202="",D202=""),"Missing period/date",IF(L202<0,"Check gross pay",IF(R202<0,"Deductions exceed gross","Review statutory amounts"))))
A204: Blue cells are inputs; green cells are formulas. PAYE/NI and statutory adjustments must be verified before approval/payment.

Sheet Payroll Calculator
A1: AVERRA STAFFING SOLUTIONS LTD | PAYROLL CALCULATOR
A2: Monthly payroll worksheet • Enter values in blue cells; formulas calculate totals.
A3: Employee & Pay Details
A4: Employee name | B4: Sandra Stasaityte | D4: Enter employee's full name
A5: Employee / payroll number | D5: Optional internal reference
A6: Job title | B6: Director
A7: Pay frequency | B7: Monthly | D7: Use monthly values in this worksheet
A8: Tax period / month | D8: e.g. October 2026
A9: Payment date
A10: Tax code | D10: Enter code from HMRC
A11: NI category | B11: A | D11: Confirm employee's applicable category
A12: Annual salary (£) | B12: 26137 | D12: Annual contractual salary, if applicable
A13: Basic gross pay (£) | B13: =IF(B12>0,B12/12,0) | D13: Calculated as annual salary ÷ 12; overwrite only if needed
A14: Overtime / bonus (£) | B14: 0
A15: Holiday / other pay (£) | B15: 0
A16: Total gross pay (£) | B16: =SUM(B13:B15) | D16: Formula
A17: PAYE income tax (£) | B17: 0 | D17: Enter verified PAYE from HMRC-compatible payroll software
A18: Employee National Insurance (£) | B18: 0 | D18: Enter verified employee NI from HMRC-compatible payroll software
A19: Employee pension (£) | B19: =ROUND(B16*B26/100,2) | D19: Formula: total gross pay × employee pension rate
A20: Other deductions (£) | B20: 0 | D20: e.g. insurance or authorised deductions
A21: Total deductions (£) | B21: =SUM(B17:B20) | D21: Formula
A22: NET PAY (£) | B22: =B16-B21 | D22: Gross pay less total deductions
A23: Employer National Insurance (£) | B23: 0 | D23: Enter verified employer NI from HMRC-compatible payroll software
A24: Employer pension contribution (£) | B24: =ROUND(B16*B27/100,2) | D24: Formula: total gross pay × employer pension rate
A25: TOTAL EMPLOYER COST (£) | B25: =B16+B23+B24 | D25: Gross pay plus employer costs
A26: Employee pension rate (%) | B26: 0 | D26: Enter percentage; employee pension is calculated from total gross pay
A27: Employer pension rate (%) | B27: 0 | D27: Enter percentage; employer pension is calculated from total gross pay
A28: Payroll check | B28: =IF(B4="","Enter employee name",IF(B8="","Enter pay period",IF(B16<0,"Check gross pay",IF(B21>B16,"Deductions exceed gross pay","Ready for review")))) | D28: Review statutory deductions and eligibility before payment

Sheet Payslip
A1: AVERRA STAFFING SOLUTIONS LTD
A2: PAYSLIP
A4: Employee | B4: ='Payroll Calculator'!B4 | C4: Pay period | D4: ='Payroll Calculator'!B8
A5: Payroll number | B5: ='Payroll Calculator'!B5 | C5: Payment date | D5: ='Payroll Calculator'!B9
A6: Job title | B6: ='Payroll Calculator'!B6 | C6: Tax code | D6: ='Payroll Calculator'!B10
A7: Pay frequency | B7: ='Payroll Calculator'!B7 | C7: NI category | D7: ='Payroll Calculator'!B11
A10: PAYMENTS | C10: DEDUCTIONS
A11: Basic gross pay | B11: ='Payroll Calculator'!B13 | C11: PAYE income tax | D11: ='Payroll Calculator'!B17
A12: Overtime / bonus | B12: ='Payroll Calculator'!B14 | C12: Employee National Insurance | D12: ='Payroll Calculator'!B18
A13: Holiday / other pay | B13: ='Payroll Calculator'!B15 | C13: Employee pension | D13: ='Payroll Calculator'!B19
A14: TOTAL GROSS PAY | B14: ='Payroll Calculator'!B16 | C14: Other deductions | D14: ='Payroll Calculator'!B20
C15: TOTAL DEDUCTIONS | D15: ='Payroll Calculator'!B21
A17: NET PAY
A18: ='Payroll Calculator'!B22
A20: Employer contributions (informational — not deducted from net pay)
A21: Employer National Insurance | B21: ='Payroll Calculator'!B23 | C21: Employer pension | D21: ='Payroll Calculator'!B24
A22: Employee / employer pension rates | B22: ='Payroll Calculator'!B26 | C22: Employer rate | D22: ='Payroll Calculator'!B27
A23: This payslip is a calculation template, not an HMRC payroll submission or confirmation of statutory compliance.

Sheet Instructions
A1: HOW TO USE THIS TEMPLATE
B3: 1
B4: Enter employee details and pay-period information in the blue cells on Payroll Calculator.
B5: 2
B6: Enter annual salary. Basic gross pay is calculated as annual salary divided by 12. Adjust basic gross pay if the employee's actual period pay differs.
B7: 3
B8: Enter overtime, bonus, holiday pay or other gross earnings as relevant.
B9: 4
A10: Enter verified PAYE income tax, employee NI and employer NI from current HMRC-compatible payroll software. These statutory calculations remain manual in this template. | B10: Enter PAYE income tax, employee National Insurance and pension deductions using verified payroll calculations for the correct tax year and pay frequency.
B11: 5
A12: Enter employee and employer pension percentages in Payroll Calculator rows 26–27. Pension amounts calculate automatically as a simple percentage of total gross pay; check scheme pensionable-pay and tax-relief rules. | B12: Enter other authorised deductions, if any. Net pay is calculated automatically as gross pay less employee deductions.
B13: 6
B14: Enter employer National Insurance and employer pension separately. These are employer costs and are not subtracted from employee net pay.
B15: 7
A16: Open the Payslip tab to view a linked summary. Save a separate copy for each employee and pay period; do not overwrite the only payroll record. | B16: Open the Payslip tab to view a print-friendly summary linked to the calculator. Update the calculator for each pay period and save a separate copy for each employee/month.
B17: IMPORTANT
A18: IMPORTANT: This workbook automates gross pay, pension estimates, deductions, net pay and employer cost arithmetic. It does NOT calculate statutory PAYE, National Insurance, student loans, statutory pay, tax-code/cumulative adjustments, pension qualifying earnings or RTI. Verify statutory amounts with current HMRC guidance or compliant payroll software before paying staff or filing RTI. | B18: This workbook does not calculate statutory PAYE, National Insurance thresholds, student-loan deductions, statutory pay, pension tax relief or tax-code adjustments. Verify these using current HMRC guidance or compliant payroll software before paying staff or filing RTI.
B19: PRIVACY
A20: Expanded workbook tabs: Employee Database, Monthly Payroll, Timesheets, Pension Tracker, Leave Tracker, Payment Tracker, Payroll Dashboard, Audit Log and Settings. | B20: Payroll data is confidential. Store the workbook securely, restrict access and avoid sending unprotected copies by email.

Sheet Timesheets
A1: AVERRA — TIMESHEETS
A2: Timesheet ID | B2: Employee ID | C2: Employee Name | D2: Week / Period Start | E2: Week / Period End | F2: Regular Hours | G2: Overtime Hours | H2: Hourly Rate (GBP) | I2: Regular Pay (GBP) | J2: Overtime Pay (GBP) | K2: Total Hours | L2: Total Earnings (GBP) | M2: Approval Status | N2: Approved By | O2: Notes
C3: =IFERROR(INDEX('Employee Database'!$B$3:$B$202,MATCH(B3,'Employee Database'!$A$3:$A$202,0)),"") | H3: =IFERROR(INDEX('Employee Database'!$K$3:$K$202,MATCH(B3,'Employee Database'!$A$3:$A$202,0)),0) | I3: =ROUND(F3*H3,2) | J3: =ROUND(G3*H3*1.5,2) | K3: =SUM(F3:G3) | L3: =SUM(I3:J3)
C4: =IFERROR(INDEX('Employee Database'!$B$3:$B$202,MATCH(B4,'Employee Database'!$A$3:$A$202,0)),"") | H4: =IFERROR(INDEX('Employee Database'!$K$3:$K$202,MATCH(B4,'Employee Database'!$A$3:$A$202,0)),0) | I4: =ROUND(F4*H4,2) | J4: =ROUND(G4*H4*1.5,2) | K4: =SUM(F4:G4) | L4: =SUM(I4:J4)
C5: =IFERROR(INDEX('Employee Database'!$B$3:$B$202,MATCH(B5,'Employee Database'!$A$3:$A$202,0)),"") | H5: =IFERROR(INDEX('Employee Database'!$K$3:$K$202,MATCH(B5,'Employee Database'!$A$3:$A$202,0)),0) | I5: =ROUND(F5*H5,2) | J5: =ROUND(G5*H5*1.5,2) | K5: =SUM(F5:G5) | L5: =SUM(I5:J5)
C6: =IFERROR(INDEX('Employee Database'!$B$3:$B$202,MATCH(B6,'Employee Database'!$A$3:$A$202,0)),"") | H6: =IFERROR(INDEX('Employee Database'!$K$3:$K$202,MATCH(B6,'Employee Database'!$A$3:$A$202,0)),0) | I6: =ROUND(F6*H6,2) | J6: =ROUND(G6*H6*1.5,2) | K6: =SUM(F6:G6) | L6: =SUM(I6:J6)
C7: =IFERROR(INDEX('Employee Database'!$B$3:$B$202,MATCH(B7,'Employee Database'!$A$3:$A$202,0)),"") | H7: =IFERROR(INDEX('Employee Database'!$K$3:$K$202,MATCH(B7,'Employee Database'!$A$3:$A$202,0)),0) | I7: =ROUND(F7*H7,2) | J7: =ROUND(G7*H7*1.5,2) | K7: =SUM(F7:G7) | L7: =SUM(I7:J7)
C8: =IFERROR(INDEX('Employee Database'!$B$3:$B$202,MATCH(B8,'Employee Database'!$A$3:$A$202,0)),"") | H8: =IFERROR(INDEX('Employee Database'!$K$3:$K$202,MATCH(B8,'Employee Database'!$A$3:$A$202,0)),0) | I8: =ROUND(F8*H8,2) | J8: =ROUND(G8*H8*1.5,2) | K8: =SUM(F8:G8) | L8: =SUM(I8:J8)
C9: =IFERROR(INDEX('Employee Database'!$B$3:$B$202,MATCH(B9,'Employee Database'!$A$3:$A$202,0)),"") | H9: =IFERROR(INDEX('Employee Database'!$K$3:$K$202,MATCH(B9,'Employee Database'!$A$3:$A$202,0)),0) | I9: =ROUND(F9*H9,2) | J9: =ROUND(G9*H9*1.5,2) | K9: =SUM(F9:G9) | L9: =SUM(I9:J9)
C10: =IFERROR(INDEX('Employee Database'!$B$3:$B$202,MATCH(B10,'Employee Database'!$A$3:$A$202,0)),"") | H10: =IFERROR(INDEX('Employee Database'!$K$3:$K$202,MATCH(B10,'Employee Database'!$A$3:$A$202,0)),0) | I10: =ROUND(F10*H10,2) | J10: =ROUND(G10*H10*1.5,2) | K10: =SUM(F10:G10) | L10: =SUM(I10:J10)
C11: =IFERROR(INDEX('Employee Database'!$B$3:$B$202,MATCH(B11,'Employee Database'!$A$3:$A$202,0)),"") | H11: =IFERROR(INDEX('Employee Database'!$K$3:$K$202,MATCH(B11,'Employee Database'!$A$3:$A$202,0)),0) | I11: =ROUND(F11*H11,2) | J11: =ROUND(G11*H11*1.5,2) | K11: =SUM(F11:G11) | L11: =SUM(I11:J11)
C12: =IFERROR(INDEX('Employee Database'!$B$3:$B$202,MATCH(B12,'Employee Database'!$A$3:$A$202,0)),"") | H12: =IFERROR(INDEX('Employee Database'!$K$3:$K$202,MATCH(B12,'Employee Database'!$A$3:$A$202,0)),0) | I12: =ROUND(F12*H12,2) | J12: =ROUND(G12*H12*1.5,2) | K12: =SUM(F12:G12) | L12: =SUM(I12:J12)
C13: =IFERROR(INDEX('Employee Database'!$B$3:$B$202,MATCH(B13,'Employee Database'!$A$3:$A$202,0)),"") | H13: =IFERROR(INDEX('Employee Database'!$K$3:$K$202,MATCH(B13,'Employee Database'!$A$3:$A$202,0)),0) | I13: =ROUND(F13*H13,2) | J13: =ROUND(G13*H13*1.5,2) | K13: =SUM(F13:G13) | L13: =SUM(I13:J13)
C14: =IFERROR(INDEX('Employee Database'!$B$3:$B$202,MATCH(B14,'Employee Database'!$A$3:$A$202,0)),"") | H14: =IFERROR(INDEX('Employee Database'!$K$3:$K$202,MATCH(B14,'Employee Database'!$A$3:$A$202,0)),0) | I14: =ROUND(F14*H14,2) | J14: =ROUND(G14*H14*1.5,2) | K14: =SUM(F14:G14) | L14: =SUM(I14:J14)
... C202: =IFERROR(INDEX('Employee Database'!$B$3:$B$202,MATCH(B202,'Employee Database'!$A$3:$A$202,0)),"") | H202: =IFERROR(INDEX('Employee Database'!$K$3:$K$202,MATCH(B202,'Employee Database'!$A$3:$A$202,0)),0) | I202: =ROUND(F202*H202,2) | J202: =ROUND(G202*H202*1.5,2) | K202: =SUM(F202:G202) | L202: =SUM(I202:J202)

Sheet Pension Tracker
A1: AVERRA — PENSION TRACKER
A2: Record ID | B2: Payroll Period | C2: Employee ID | D2: Employee Name | E2: Employee Contribution (GBP) | F2: Employer Contribution (GBP) | G2: Total Contribution (GBP) | H2: Payment Date | I2: Provider / Scheme | J2: Remittance Status | K2: Reference | L2: Notes
D3: =IFERROR(INDEX('Employee Database'!$B$3:$B$202,MATCH(C3,'Employee Database'!$A$3:$A$202,0)),"") | G3: =SUM(E3:F3)
D4: =IFERROR(INDEX('Employee Database'!$B$3:$B$202,MATCH(C4,'Employee Database'!$A$3:$A$202,0)),"") | G4: =SUM(E4:F4)
D5: =IFERROR(INDEX('Employee Database'!$B$3:$B$202,MATCH(C5,'Employee Database'!$A$3:$A$202,0)),"") | G5: =SUM(E5:F5)
D6: =IFERROR(INDEX('Employee Database'!$B$3:$B$202,MATCH(C6,'Employee Database'!$A$3:$A$202,0)),"") | G6: =SUM(E6:F6)
D7: =IFERROR(INDEX('Employee Database'!$B$3:$B$202,MATCH(C7,'Employee Database'!$A$3:$A$202,0)),"") | G7: =SUM(E7:F7)
D8: =IFERROR(INDEX('Employee Database'!$B$3:$B$202,MATCH(C8,'Employee Database'!$A$3:$A$202,0)),"") | G8: =SUM(E8:F8)
D9: =IFERROR(INDEX('Employee Database'!$B$3:$B$202,MATCH(C9,'Employee Database'!$A$3:$A$202,0)),"") | G9: =SUM(E9:F9)
D10: =IFERROR(INDEX('Employee Database'!$B$3:$B$202,MATCH(C10,'Employee Database'!$A$3:$A$202,0)),"") | G10: =SUM(E10:F10)
D11: =IFERROR(INDEX('Employee Database'!$B$3:$B$202,MATCH(C11,'Employee Database'!$A$3:$A$202,0)),"") | G11: =SUM(E11:F11)
D12: =IFERROR(INDEX('Employee Database'!$B$3:$B$202,MATCH(C12,'Employee Database'!$A$3:$A$202,0)),"") | G12: =SUM(E12:F12)
D13: =IFERROR(INDEX('Employee Database'!$B$3:$B$202,MATCH(C13,'Employee Database'!$A$3:$A$202,0)),"") | G13: =SUM(E13:F13)
D14: =IFERROR(INDEX('Employee Database'!$B$3:$B$202,MATCH(C14,'Employee Database'!$A$3:$A$202,0)),"") | G14: =SUM(E14:F14)
... D202: =IFERROR(INDEX('Employee Database'!$B$3:$B$202,MATCH(C202,'Employee Database'!$A$3:$A$202,0)),"") | G202: =SUM(E202:F202)

Sheet Leave Tracker
A1: AVERRA — LEAVE TRACKER
A2: Request ID | B2: Employee ID | C2: Employee Name | D2: Leave Type | E2: Start Date | F2: End Date | G2: Working Days | H2: Paid? | I2: Approval Status | J2: Approved By | K2: Notes
C3: =IFERROR(INDEX('Employee Database'!$B$3:$B$202,MATCH(B3,'Employee Database'!$A$3:$A$202,0)),"") | G3: =IF(OR(E3="",F3=""),"",NETWORKDAYS(E3,F3))
C4: =IFERROR(INDEX('Employee Database'!$B$3:$B$202,MATCH(B4,'Employee Database'!$A$3:$A$202,0)),"") | G4: =IF(OR(E4="",F4=""),"",NETWORKDAYS(E4,F4))
C5: =IFERROR(INDEX('Employee Database'!$B$3:$B$202,MATCH(B5,'Employee Database'!$A$3:$A$202,0)),"") | G5: =IF(OR(E5="",F5=""),"",NETWORKDAYS(E5,F5))
C6: =IFERROR(INDEX('Employee Database'!$B$3:$B$202,MATCH(B6,'Employee Database'!$A$3:$A$202,0)),"") | G6: =IF(OR(E6="",F6=""),"",NETWORKDAYS(E6,F6))
C7: =IFERROR(INDEX('Employee Database'!$B$3:$B$202,MATCH(B7,'Employee Database'!$A$3:$A$202,0)),"") | G7: =IF(OR(E7="",F7=""),"",NETWORKDAYS(E7,F7))
C8: =IFERROR(INDEX('Employee Database'!$B$3:$B$202,MATCH(B8,'Employee Database'!$A$3:$A$202,0)),"") | G8: =IF(OR(E8="",F8=""),"",NETWORKDAYS(E8,F8))
C9: =IFERROR(INDEX('Employee Database'!$B$3:$B$202,MATCH(B9,'Employee Database'!$A$3:$A$202,0)),"") | G9: =IF(OR(E9="",F9=""),"",NETWORKDAYS(E9,F9))
C10: =IFERROR(INDEX('Employee Database'!$B$3:$B$202,MATCH(B10,'Employee Database'!$A$3:$A$202,0)),"") | G10: =IF(OR(E10="",F10=""),"",NETWORKDAYS(E10,F10))
C11: =IFERROR(INDEX('Employee Database'!$B$3:$B$202,MATCH(B11,'Employee Database'!$A$3:$A$202,0)),"") | G11: =IF(OR(E11="",F11=""),"",NETWORKDAYS(E11,F11))
C12: =IFERROR(INDEX('Employee Database'!$B$3:$B$202,MATCH(B12,'Employee Database'!$A$3:$A$202,0)),"") | G12: =IF(OR(E12="",F12=""),"",NETWORKDAYS(E12,F12))
C13: =IFERROR(INDEX('Employee Database'!$B$3:$B$202,MATCH(B13,'Employee Database'!$A$3:$A$202,0)),"") | G13: =IF(OR(E13="",F13=""),"",NETWORKDAYS(E13,F13))
C14: =IFERROR(INDEX('Employee Database'!$B$3:$B$202,MATCH(B14,'Employee Database'!$A$3:$A$202,0)),"") | G14: =IF(OR(E14="",F14=""),"",NETWORKDAYS(E14,F14))
... C202: =IFERROR(INDEX('Employee Database'!$B$3:$B$202,MATCH(B202,'Employee Database'!$A$3:$A$202,0)),"") | G202: =IF(OR(E202="",F202=""),"",NETWORKDAYS(E202,F202))

Sheet Payment Tracker
A1: AVERRA — PAYMENT TRACKER
A2: Payment ID | B2: Payroll ID | C2: Pay Date | D2: Employee ID | E2: Employee Name | F2: Net Pay (GBP) | G2: Payment Status | H2: Paid Date | I2: Bank / Method | J2: Transaction Reference | K2: Reconciled? | L2: Notes
E3: =IFERROR(INDEX('Employee Database'!$B$3:$B$202,MATCH(D3,'Employee Database'!$A$3:$A$202,0)),"") | F3: =IFERROR(INDEX('Monthly Payroll'!$R$3:$R$202,MATCH(B3,'Monthly Payroll'!$A$3:$A$202,0)),0)
E4: =IFERROR(INDEX('Employee Database'!$B$3:$B$202,MATCH(D4,'Employee Database'!$A$3:$A$202,0)),"") | F4: =IFERROR(INDEX('Monthly Payroll'!$R$3:$R$202,MATCH(B4,'Monthly Payroll'!$A$3:$A$202,0)),0)
E5: =IFERROR(INDEX('Employee Database'!$B$3:$B$202,MATCH(D5,'Employee Database'!$A$3:$A$202,0)),"") | F5: =IFERROR(INDEX('Monthly Payroll'!$R$3:$R$202,MATCH(B5,'Monthly Payroll'!$A$3:$A$202,0)),0)
E6: =IFERROR(INDEX('Employee Database'!$B$3:$B$202,MATCH(D6,'Employee Database'!$A$3:$A$202,0)),"") | F6: =IFERROR(INDEX('Monthly Payroll'!$R$3:$R$202,MATCH(B6,'Monthly Payroll'!$A$3:$A$202,0)),0)
E7: =IFERROR(INDEX('Employee Database'!$B$3:$B$202,MATCH(D7,'Employee Database'!$A$3:$A$202,0)),"") | F7: =IFERROR(INDEX('Monthly Payroll'!$R$3:$R$202,MATCH(B7,'Monthly Payroll'!$A$3:$A$202,0)),0)
E8: =IFERROR(INDEX('Employee Database'!$B$3:$B$202,MATCH(D8,'Employee Database'!$A$3:$A$202,0)),"") | F8: =IFERROR(INDEX('Monthly Payroll'!$R$3:$R$202,MATCH(B8,'Monthly Payroll'!$A$3:$A$202,0)),0)
E9: =IFERROR(INDEX('Employee Database'!$B$3:$B$202,MATCH(D9,'Employee Database'!$A$3:$A$202,0)),"") | F9: =IFERROR(INDEX('Monthly Payroll'!$R$3:$R$202,MATCH(B9,'Monthly Payroll'!$A$3:$A$202,0)),0)
E10: =IFERROR(INDEX('Employee Database'!$B$3:$B$202,MATCH(D10,'Employee Database'!$A$3:$A$202,0)),"") | F10: =IFERROR(INDEX('Monthly Payroll'!$R$3:$R$202,MATCH(B10,'Monthly Payroll'!$A$3:$A$202,0)),0)
E11: =IFERROR(INDEX('Employee Database'!$B$3:$B$202,MATCH(D11,'Employee Database'!$A$3:$A$202,0)),"") | F11: =IFERROR(INDEX('Monthly Payroll'!$R$3:$R$202,MATCH(B11,'Monthly Payroll'!$A$3:$A$202,0)),0)
E12: =IFERROR(INDEX('Employee Database'!$B$3:$B$202,MATCH(D12,'Employee Database'!$A$3:$A$202,0)),"") | F12: =IFERROR(INDEX('Monthly Payroll'!$R$3:$R$202,MATCH(B12,'Monthly Payroll'!$A$3:$A$202,0)),0)
E13: =IFERROR(INDEX('Employee Database'!$B$3:$B$202,MATCH(D13,'Employee Database'!$A$3:$A$202,0)),"") | F13: =IFERROR(INDEX('Monthly Payroll'!$R$3:$R$202,MATCH(B13,'Monthly Payroll'!$A$3:$A$202,0)),0)
E14: =IFERROR(INDEX('Employee Database'!$B$3:$B$202,MATCH(D14,'Employee Database'!$A$3:$A$202,0)),"") | F14: =IFERROR(INDEX('Monthly Payroll'!$R$3:$R$202,MATCH(B14,'Monthly Payroll'!$A$3:$A$202,0)),0)
... E202: =IFERROR(INDEX('Employee Database'!$B$3:$B$202,MATCH(D202,'Employee Database'!$A$3:$A$202,0)),"") | F202: =IFERROR(INDEX('Monthly Payroll'!$R$3:$R$202,MATCH(B202,'Monthly Payroll'!$A$3:$A$202,0)),0)

Sheet Audit Log
A1: AVERRA — PAYROLL AUDIT LOG
A2: Date / Time | B2: User | C2: Record Type | D2: Record ID | E2: Field Changed | F2: Old Value | G2: New Value | H2: Reason / Approval
A204: Manual audit log only; Excel formulas do not automatically capture edit history. Use controlled storage/version history for stronger auditability.

Sheet Settings
A1: AVERRA — PAYROLL SETTINGS | B1: Value | C1: Notes
A2: Company Name | B2: AVERRA STAFFING SOLUTIONS LTD | C2: Edit if company name changes
A3: Default Currency | B3: GBP | C3: Currency for UK payroll register
A4: Payroll Year | B4: 2026 | C4: Dashboard year can be changed separately
A5: Standard Hours per Week | B5: 37.5 | C5: Reference only; check employment contracts
A6: Default Overtime Multiplier | B6: 1.5 | C6: Timesheets uses 1.5×; change formulas if policy differs
A7: PAYE / NI Source | B7: Verified payroll software | C7: Do not use this workbook as a statutory tax calculator
A8: Pension Basis | B8: Simple percentage of gross pay | C8: Confirm scheme qualifying earnings, thresholds and tax relief
A9: UK Tax Year Start | B9: 06-Apr | C9: UK tax year generally runs 6 April to 5 April
A10: Data Protection | B10: Restricted access | C10: Store only necessary data and protect workbook
A11: Workbook Scope | B11: Payroll tracking and arithmetic | C11: Not HMRC RTI submission software or a substitute for compliant payroll
